[
  { "id": "1", "name": "Kabellose Kopfhörer ProX", "category": "Elektronik", "price": 79.99, "oldPrice": 129.99, "rating": 4.7, "reviews": 1243, "emoji": "🎧", "badge": "Bestseller" },
  { "id": "2", "name": "Ergonomischer Schreibtischstuhl", "category": "Büro & Einrichtung", "price": 199.00, "oldPrice": 299.00, "rating": 4.5, "reviews": 587, "emoji": "🪑", "badge": "Sale" },
  { "id": "3", "name": "Kaffeemaschine Barista Pro", "category": "Küche", "price": 89.95, "oldPrice": null, "rating": 4.8, "reviews": 2104, "emoji": "☕", "badge": null },
  { "id": "4", "name": "Yoga-Matte Premium", "category": "Sport & Fitness", "price": 39.90, "oldPrice": 59.90, "rating": 4.6, "reviews": 891, "emoji": "🧘", "badge": "Sale" },
  { "id": "5", "name": "Roman: Das stille Haus", "category": "Bücher", "price": 14.99, "oldPrice": null, "rating": 4.9, "reviews": 3456, "emoji": "📚", "badge": "Top" },
  { "id": "6", "name": "Smartwatch FitTrack 5", "category": "Elektronik", "price": 149.00, "oldPrice": 199.00, "rating": 4.4, "reviews": 672, "emoji": "⌚", "badge": "Neu" },
  { "id": "7", "name": "Gewürzset Weltküche (12er)", "category": "Lebensmittel", "price": 24.99, "oldPrice": null, "rating": 4.7, "reviews": 445, "emoji": "🧂", "badge": null },
  { "id": "8", "name": "Pflanzgefäß Set (3er)", "category": "Garten", "price": 19.90, "oldPrice": 29.90, "rating": 4.3, "reviews": 213, "emoji": "🪴", "badge": "Sale" }
]
